astromodule/__init__.py
astromodule/adql.py
astromodule/automl.py
astromodule/cli.py
astromodule/datamodel.py
astromodule/distance.py
astromodule/hp.py
astromodule/io.py
astromodule/legacy.py
astromodule/network.py
astromodule/pipeline.py
astromodule/plot.py
astromodule/service.py
astromodule/splus.py
astromodule/table.py
astromodule/tap.py
astromodule/utils.py
astromodule-0.10.10.dist-info/METADATA
astromodule-0.10.10.dist-info/WHEEL
astromodule-0.10.10.dist-info/entry_points.txt
astromodule-0.10.10.dist-info/top_level.txt
astromodule-0.10.10.dist-info/RECORD
