Metadata-Version: 2.4
Name: astromodule
Version: 0.10.10
Summary: Astronomy Tools
Author: Natanael Magalhães Cardoso
Author-email: Natanael Magalhães Cardoso <contact@natanael.net>
Maintainer: Natanael Magalhães Cardoso
Maintainer-email: Natanael Magalhães Cardoso <contact@natanael.net>
Project-URL: Homepage, https://nmcardoso.github.io/astromodule
Project-URL: Documentation, https://nmcardoso.github.io/astromodule
Project-URL: Repository, https://github.com/nmcardoso/astromodule
Project-URL: Issues, https://github.com/nmcardoso/astromodule/issues
Project-URL: Changelog, https://github.com/nmcardoso/astromodule/blob/main/CHANGELOG.md
Keywords: astronomy,machine learning,data science
Requires-Python: >=3.8
Requires-Dist: wheel
Requires-Dist: numpy>=1.21.6
Requires-Dist: pandas>=1.3.5
Requires-Dist: tqdm>=4.64.1
Requires-Dist: requests>=2.23
Requires-Dist: Pillow>=7.1.2
Requires-Dist: astropy>=5.2
Requires-Dist: matplotlib
Requires-Dist: optuna
Provides-Extra: docs
Requires-Dist: Jinja2>=3.1; extra == "docs"
Requires-Dist: sphinx; extra == "docs"
Requires-Dist: sphinx_copybutton; extra == "docs"
Requires-Dist: sphinx-astropy; extra == "docs"
Requires-Dist: sphinx-gallery; extra == "docs"
Requires-Dist: sphinx-automodapi; extra == "docs"
Requires-Dist: numpydoc; extra == "docs"
Requires-Dist: furo; extra == "docs"
Requires-Dist: pydata-sphinx-theme; extra == "docs"
Requires-Dist: ipykernel; extra == "docs"
Dynamic: author
Dynamic: description
Dynamic: description-content-type
Dynamic: maintainer
